PyAuth-1.3.0.data/data/share/doc/PyAuth/LICENSE.html
PyAuth-1.3.0.data/data/share/doc/PyAuth/PyAuth.desktop
PyAuth-1.3.0.data/data/share/doc/PyAuth/README.rst
PyAuth-1.3.0.data/data/share/doc/PyAuth/TODO.md
PyAuth-1.3.0.data/data/share/doc/PyAuth/VERSIONS.md
PyAuth-1.3.0.data/data/share/icons/hicolor/128x128/apps/PyAuth-dark.png
PyAuth-1.3.0.data/data/share/icons/hicolor/128x128/apps/PyAuth-grey.png
PyAuth-1.3.0.data/data/share/icons/hicolor/128x128/apps/PyAuth-white.png
PyAuth-1.3.0.data/data/share/icons/hicolor/128x128/apps/PyAuth.png
PyAuth-1.3.0.data/data/share/icons/hicolor/16x16/apps/PyAuth-dark.png
PyAuth-1.3.0.data/data/share/icons/hicolor/16x16/apps/PyAuth-grey.png
PyAuth-1.3.0.data/data/share/icons/hicolor/16x16/apps/PyAuth-white.png
PyAuth-1.3.0.data/data/share/icons/hicolor/16x16/apps/PyAuth.png
PyAuth-1.3.0.data/data/share/icons/hicolor/24x24/apps/PyAuth-dark.png
PyAuth-1.3.0.data/data/share/icons/hicolor/24x24/apps/PyAuth-grey.png
PyAuth-1.3.0.data/data/share/icons/hicolor/24x24/apps/PyAuth-white.png
PyAuth-1.3.0.data/data/share/icons/hicolor/24x24/apps/PyAuth.png
PyAuth-1.3.0.data/data/share/icons/hicolor/256x256/apps/PyAuth-dark.png
PyAuth-1.3.0.data/data/share/icons/hicolor/256x256/apps/PyAuth-grey.png
PyAuth-1.3.0.data/data/share/icons/hicolor/256x256/apps/PyAuth-white.png
PyAuth-1.3.0.data/data/share/icons/hicolor/256x256/apps/PyAuth.png
PyAuth-1.3.0.data/data/share/icons/hicolor/32x32/apps/PyAuth-dark.png
PyAuth-1.3.0.data/data/share/icons/hicolor/32x32/apps/PyAuth-grey.png
PyAuth-1.3.0.data/data/share/icons/hicolor/32x32/apps/PyAuth-white.png
PyAuth-1.3.0.data/data/share/icons/hicolor/32x32/apps/PyAuth.png
PyAuth-1.3.0.data/data/share/icons/hicolor/48x48/apps/PyAuth-dark.png
PyAuth-1.3.0.data/data/share/icons/hicolor/48x48/apps/PyAuth-grey.png
PyAuth-1.3.0.data/data/share/icons/hicolor/48x48/apps/PyAuth-white.png
PyAuth-1.3.0.data/data/share/icons/hicolor/48x48/apps/PyAuth.png
PyAuth-1.3.0.dist-info/DESCRIPTION.rst
PyAuth-1.3.0.dist-info/METADATA
PyAuth-1.3.0.dist-info/RECORD
PyAuth-1.3.0.dist-info/WHEEL
PyAuth-1.3.0.dist-info/entry_points.txt
PyAuth-1.3.0.dist-info/metadata.json
PyAuth-1.3.0.dist-info/top_level.txt
