Metadata-Version: 2.0
Name: PyAuth
Version: 1.3.0
Summary: Google Authenticator (TOTP) desktop client
Home-page: https://github.com/tknarr/PyAuth
Author: Todd Knarr
Author-email: tknarr@silverglass.org
License: GPLv3+
Keywords: authentication totp hotp 2fa
Platform: UNKNOWN
Classifier: Development Status :: 4 - Beta
Classifier: Intended Audience :: End Users/Desktop
Classifier: Topic :: Security
Classifier: License :: OSI Approved :: GNU General Public License v3 or later (GPLv3+)
Classifier: Programming Language :: Python :: 2
Classifier: Programming Language :: Python :: 2.7
Classifier: Programming Language :: Python :: 3
Classifier: Programming Language :: Python :: 3.4
Classifier: Environment :: X11 Applications
Classifier: Operating System :: Unix
Requires-Dist: wxPython (~=3.0)
Requires-Dist: pyotp (~=2.2)
Requires-Dist: cryptography (~=2.3)
Requires-Dist: qrcode (~=6.0)
Requires-Dist: Pillow (~=5.3)
Requires-Dist: zbarlight (~=2.1)
